py4devs_api/__init__.py
py4devs_api/api_test.py
py4devs_api-0.3.0.dist-info/LICENSE.txt
py4devs_api-0.3.0.dist-info/METADATA
py4devs_api-0.3.0.dist-info/WHEEL
py4devs_api-0.3.0.dist-info/top_level.txt
py4devs_api-0.3.0.dist-info/RECORD
